otus/__init__.py
otus/core.py
otus/main.py
otus_2020-0.1.dist-info/METADATA
otus_2020-0.1.dist-info/WHEEL
otus_2020-0.1.dist-info/entry_points.txt
otus_2020-0.1.dist-info/top_level.txt
otus_2020-0.1.dist-info/RECORD
