Metadata-Version: 2.1
Name: otus-2020
Version: 0.1
Summary: famous quotes
Home-page: https://github.com/DanteOnline/django-dantejcoder
Author: MR
Author-email: mr@gmail.com
License: GNU General Public License v3.0
Keywords: json,django,JsonResponse,encoder
Platform: UNKNOWN
